drf_file_manager/__init__.py
drf_file_manager/apps.py
drf_file_manager/models.py
drf_file_manager/serializers.py
drf_file_manager/urls.py
drf_file_manager/utils.py
drf_file_manager/views.py
drf_file_manager/migrations/0001_initial.py
drf_file_manager/migrations/__init__.py
drf_file_manager/version/version.json
drf_file_manager-1.0.0.dist-info/METADATA
drf_file_manager-1.0.0.dist-info/WHEEL
drf_file_manager-1.0.0.dist-info/top_level.txt
drf_file_manager-1.0.0.dist-info/RECORD
